proyecto_eval/__init__.py
proyecto_eval-0.0.1.dist-info/METADATA
proyecto_eval-0.0.1.dist-info/WHEEL
proyecto_eval-0.0.1.dist-info/top_level.txt
proyecto_eval-0.0.1.dist-info/RECORD
