Metadata-Version: 2.4
Name: proyecto-eval
Version: 0.0.1
Summary: Evaluation phase package (CRISP-DM)
Author: Angel Castellanos, Alejandro Azurdia, Diego Morales
Requires-Python: >=3.8
Requires-Dist: proyecto-core==0.0.1
Requires-Dist: scikit-learn>=1.0.0
Requires-Dist: pandas>=2.0.0
Requires-Dist: numpy>=1.20.0
Dynamic: author
Dynamic: requires-dist
Dynamic: requires-python
Dynamic: summary
